LICENSE
MANIFEST.in
README.rst
setup.py
bin/eloquent
eloquent/__init__.py
eloquent/database_manager.py
eloquent/version.py
eloquent.egg-info/PKG-INFO
eloquent.egg-info/SOURCES.txt
eloquent.egg-info/dependency_links.txt
eloquent.egg-info/requires.txt
eloquent.egg-info/top_level.txt
eloquent/commands/__init__.py
eloquent/commands/application.py
eloquent/commands/migrations/__init__.py
eloquent/commands/migrations/base_command.py
eloquent/commands/migrations/install_command.py
eloquent/commands/migrations/make_command.py
eloquent/commands/migrations/migrate_command.py
eloquent/commands/migrations/reset_command.py
eloquent/commands/migrations/rollback_command.py
eloquent/commands/migrations/status_command.py
eloquent/connections/__init__.py
eloquent/connections/connection.py
eloquent/connections/connection_interface.py
eloquent/connections/connection_resolver_interface.py
eloquent/connections/mysql_connection.py
eloquent/connections/postgres_connection.py
eloquent/connections/sqlite_connection.py
eloquent/connectors/__init__.py
eloquent/connectors/connection_factory.py
eloquent/connectors/connector.py
eloquent/connectors/mysql_connector.py
eloquent/connectors/postgres_connector.py
eloquent/connectors/sqlite_connector.py
eloquent/dbal/__init__.py
eloquent/dbal/column.py
eloquent/dbal/column_diff.py
eloquent/dbal/comparator.py
eloquent/dbal/mysql_schema_manager.py
eloquent/dbal/postgres_schema_manager.py
eloquent/dbal/schema_manager.py
eloquent/dbal/sqlite_schema_manager.py
eloquent/dbal/table.py
eloquent/dbal/table_diff.py
eloquent/dbal/platforms/__init__.py
eloquent/dbal/platforms/mysql_platform.py
eloquent/dbal/platforms/platform.py
eloquent/dbal/platforms/postgres_platform.py
eloquent/dbal/platforms/sqlite_platform.py
eloquent/dbal/types/__init__.py
eloquent/exceptions/__init__.py
eloquent/exceptions/connection.py
eloquent/exceptions/connectors.py
eloquent/exceptions/orm.py
eloquent/exceptions/query.py
eloquent/migrations/__init__.py
eloquent/migrations/database_migration_repository.py
eloquent/migrations/migration.py
eloquent/migrations/migration_creator.py
eloquent/migrations/migrator.py
eloquent/migrations/stubs.py
