Metadata-Version: 1.1
Name: eloquent
Version: 0.5
Summary: The Eloquent ORM provides a simple yet beautiful ActiveRecord implementation.
Home-page: https://github.com/sdispater/eloquent
Author: Sébastien Eustace
Author-email: sebastien.eustace@gmail.com
License: MIT
Download-URL: https://github.com/sdispater/eloquent/archive/0.5.tar.gz
Platform: UNKNOWN
Classifier: Intended Audience :: Developers
Classifier: Operating System :: OS Independent
Classifier: Programming Language :: Python
Classifier: Topic :: Software Development :: Libraries :: Python Modules
